{
  "app": "tonights-tasks-bingo",
  "version": 1,
  "updatedAt": 1784149322068,
  "boardGeneration": 1,
  "exportedAt": "2026-07-15T21:02:02.068Z",
  "tasks": [
    {
      "id": "t_mrmj5jha_nc7fl1",
      "name": "Plate Audit",
      "description": "Gather all the plates in a consolidated area and post a photo of all the plates in the teams chat prior to marking this task completed",
      "completed": false,
      "createdAt": 1784147160286,
      "updatedAt": 1784147160286
    },
    {
      "id": "t_mrmj5k3d_154rpu",
      "name": "Loaner Audit",
      "description": "Using Mission Control via garage, filter for service loaners in Cypress and verify there are no loaners stored at offsite. If there are any loaners stored at offsite, quickly retrieve them before marking this task completed.",
      "completed": false,
      "createdAt": 1784147161081,
      "updatedAt": 1784147161081
    },
    {
      "id": "t_mrmjgp90_enmwx9",
      "name": "Box Audit",
      "description": "Take all the keys from the offsite key drop off box and post a photo in the teams chat to confirm keys have been grabbed.",
      "completed": false,
      "createdAt": 1784147680980,
      "updatedAt": 1784147680980
    },
    {
      "id": "t_mrmjlha0_gxbsls",
      "name": "Clear Overflow",
      "description": "Audit vehicles in overflow parking and kick out any vehicles with either no date, or a date 2+ days out.",
      "completed": false,
      "createdAt": 1784147903928,
      "updatedAt": 1784147903928
    },
    {
      "id": "t_mrmjtjuw_ogfwnc",
      "name": "Clear Trade-in Parking",
      "description": "Open up every space in the trade-in parking zone.",
      "completed": false,
      "createdAt": 1784148280520,
      "updatedAt": 1784148280520
    },
    {
      "id": "t_mrmjy8zy_dk6g78",
      "name": "Pull and Charge next days cars",
      "description": "",
      "completed": false,
      "createdAt": 1784148499726,
      "updatedAt": 1784148499726
    },
    {
      "id": "t_mrmjz1y5_eegu2g",
      "name": "Pull-Onsite all cars for the day after tomorrow",
      "description": "",
      "completed": false,
      "createdAt": 1784148537245,
      "updatedAt": 1784148537245
    },
    {
      "id": "t_mrmkfu69_oahi2e",
      "name": "Sync test",
      "description": "",
      "completed": false,
      "createdAt": 1784149320321,
      "updatedAt": 1784149320321
    }
  ],
  "savedTasks": [
    {
      "id": "s_mrmjtizk_dq7s7k",
      "name": "Clear Trade-in Parking",
      "description": "Open up every space in the trade-in parking zone.",
      "createdAt": 1784148279392
    },
    {
      "id": "s_mrmj0vz6_gfqsa2",
      "name": "Plate Audit",
      "description": "Gather all the plates in a consolidated area and post a photo of all the plates in the teams chat prior to marking this task completed",
      "createdAt": 1784146943202
    },
    {
      "id": "s_mrmj43b5_hy9b1w",
      "name": "Loaner Audit",
      "description": "Using Mission Control via garage, filter for service loaners in Cypress and verify there are no loaners stored at offsite. If there are any loaners stored at offsite, quickly retrieve them before marking this task completed.",
      "createdAt": 1784147092673
    },
    {
      "id": "s_mrmjnzh3_rai5t9",
      "name": "Clear Overflow",
      "description": "Audit overflow parking and kick outside any vehicles either with no date or scheduled 2+ days later. If the vehicle is scheduled for the following day pull it into QC, if the vehicle is scheduled for the day after, put it back into the washline.",
      "createdAt": 1784148020823
    },
    {
      "id": "s_mrmjgl7l_3aeuo9",
      "name": "Box Audit",
      "description": "Take all the keys from the offsite key drop off box and post a photo in the teams chat to confirm keys have been grabbed.",
      "createdAt": 1784147675745
    }
  ]
}